LICENSE
MANIFEST.in
README.md
README.rst
VERSION
requirements.txt
setup.py
bin/demodocus
demodocus/__init__.py
demodocus/__main__.py
demodocus/command_line.py
demodocus/utilities.py
demodocus.egg-info/PKG-INFO
demodocus.egg-info/SOURCES.txt
demodocus.egg-info/dependency_links.txt
demodocus.egg-info/requires.txt
demodocus.egg-info/top_level.txt
demodocus/res/sample.json
demodocus/res/sample.mp3
demodocus/res/sample.ssv
demodocus/res/sample.ssvh