Metadata-Version: 1.1
Name: demodocus
Version: 1.0.0.1
Summary: demodocus is Python CLI program to quickly check synchronization maps
Home-page: https://github.com/pettarin/demodocus
Author: Alberto Pettarin
Author-email: alberto@albertopettarin.it
License: MIT License
Keywords: JSON,SSV,SSVH,aeneas,audio,demodocus,ffmpeg,portaudio,pyaudio,synchronization map
Platform: UNKNOWN
Classifier: Development Status :: 5 - Production/Stable
Classifier: Environment :: Console
Classifier: Intended Audience :: Developers
Classifier: Intended Audience :: End Users/Desktop
Classifier: License :: OSI Approved :: MIT License
Classifier: Natural Language :: English
Classifier: Operating System :: MacOS :: MacOS X
Classifier: Operating System :: Microsoft :: Windows
Classifier: Operating System :: POSIX :: Linux
Classifier: Programming Language :: Python
Classifier: Programming Language :: Python :: 2
Classifier: Programming Language :: Python :: 2.7
Classifier: Programming Language :: Python :: 3
Classifier: Programming Language :: Python :: 3.4
Classifier: Programming Language :: Python :: 3.5
Classifier: Topic :: Education
Classifier: Topic :: Multimedia
Classifier: Topic :: Multimedia :: Sound/Audio
Classifier: Topic :: Multimedia :: Sound/Audio :: Analysis
Classifier: Topic :: Multimedia :: Sound/Audio :: Speech
Classifier: Topic :: Software Development :: Libraries :: Python Modules
Classifier: Topic :: Text Processing
Classifier: Topic :: Text Processing :: Linguistic
Classifier: Topic :: Text Processing :: Markup
Classifier: Topic :: Text Processing :: Markup :: HTML
Classifier: Topic :: Text Processing :: Markup :: XML
Classifier: Topic :: Utilities
